gandip.py
gandip-3.0.0.dist-info/METADATA
gandip-3.0.0.dist-info/WHEEL
gandip-3.0.0.dist-info/entry_points.txt
gandip-3.0.0.dist-info/top_level.txt
gandip-3.0.0.dist-info/RECORD
