Metadata-Version: 2.1
Name: gandip
Version: 3.0.0
Summary: Keep your gandi DNS records up to date with your current IP
Home-page: https://github.com/ArnaudLevaufre/GandIP
Author: Arnaud Levaufre
Author-email: arnaud@levaufre.name
License: MIT
Keywords: dns gandi ip selfhosting hosting
Platform: UNKNOWN
Classifier: Development Status :: 5 - Production/Stable
Classifier: Intended Audience :: Developers
Classifier: Intended Audience :: System Administrators
Classifier: Intended Audience :: End Users/Desktop
Classifier: Topic :: Internet :: Name Service (DNS)
Classifier: License :: OSI Approved :: MIT License
Classifier: Programming Language :: Python :: 3.6
